{
   "name":"L1ST",
   "semestre1":{
      "name":"S1",
      "unites":[
         {
            "name":"U1_S1",
            "title":"Fondamentale",
            "modules":[
               {
                  "name":"Analyse1",
                  "title":"Analyse 1",
                  "coef":3,
                  "credit":6,
                  "poids":[
                     60,
                     40,
                     0
                  ],
                  "poids_tp":0,
                  "poids_td":0.4,
                  "poids_exam":0.6,
                  "moy":0
               },
              {
                  "name":"Algèbre1",
                  "title":"Algèbre 1",
                  "coef":2,
                  "credit":4,
                  "poids":[
                     60,
                     40,
                     0
                  ],
                  "poids_tp":0,
                  "poids_td":0.4,
                  "poids_exam":0.6,
                  "moy":0
               },
               ],
                           "coef":5,
            "credit":0,
            "credits_origine":10,
            "moy":0
            },
               {
                  "name":"U2_S1",
            "title":"Fondamentale",
            "modules":[
               {
                  "name":"Meca",
                  "title":"Elément de mécanique",
                  "coef":3,
                  "credit":6,
                  "poids":[
                     60,
                     40,
                     0
                  ],
                  "poids_tp":0,
                  "poids_td":0.4,
                  "poids_exam":0.6,
                  "moy":0
               },
               {
                  "name":"sm",
                  "title":"Structure de la matière",
                  "coef":3,
                  "credit":6,
                  "poids":[
                     60,
                     40,
                     0
                  ],
                  "poids_tp":0,
                  "poids_td":0.4,
                  "poids_exam":0.6,
                  "moy":0
               }
            ],
            "coef":6,
            "credit":0,
            "credits_origine":12,
            "moy":0
         },
         
         {
            "name":"U3_S1",
            "title":"Méthodologique",
            "modules":[
               {
                  "name":"TPmeca1",
                  "title":"TP Elément de mécanique",
                  "coef":1,
                  "credit":2,
                  "poids":[
                     0,
                     0,
                     100
                  ],
                  "poids_tp":1,
                  "poids_td":0,
                  "poids_exam":0,
                  "moy":0
               },
               {
                  "name":"TPSM",
                  "title":"TP Structure de la matière",
                  "coef":1,
                  "credit":2,
                  "poids":[
                     0,
                     0,
                     100
                  ],
                  "poids_tp":1,
                  "poids_td":0,
                  "poids_exam":0,
                  "moy":0
               },
               {
                  "name":"info1",
                  "title":"Structure des ordinateurs et applications",
                  "coef":2,
                  "credit":2,
                  "poids":[
                     60,
                     0,
                     40
                  ],
                  "poids_tp":0.4,
                  "poids_td":0,
                  "poids_exam":0.6,
                  "moy":0
               }
            ],
            "coef":4,
            "credit":0,
            "credits_origine":6,
            "moy":0
         },
         {
            "name":"U4_S1",
            "title":"Transversale",
            "modules":[
               {
                  "name":"DED",
                  "title":"Dimension éthique et déontologique (les fondements)",
                  "coef":1,
                  "credit":1,
                  "poids":[
                     100,
                     0,
                     0
                  ],
                  "poids_tp":0,
                  "poids_td":0,
                  "poids_exam":1,
                  "moy":0
               },
                {
                  "name":"MST1",
                  "title":"Les métiers en Sciences et Technologies 1",
                  "coef":1,
                  "credit":1,
                  "poids":[
                     100,
                     0,
                     0
                  ],
                  "poids_tp":0,
                  "poids_td":0,
                  "poids_exam":1,
                  "moy":0
               }
            ],
            "coef":2,
            "credit":0,
            "credits_origine":2,
            "moy":0
         },
      
      ],
      "moy":0,
      "coef":17,
      "credits_origine":30
   },
   "semestre2":{
      "name":"S2",
      "unites":[
               {
            "name":"U1_S2",
            "title":"Fondamentale",
            "modules":[
               {
                  "name":"Analyse2",
                  "title":"Algèbre 2",
                  "coef":3,
                  "credit":6,
                  "poids":[
                     60,
                     40,
                     0
                  ],
                  "poids_tp":0,
                  "poids_td":0.4,
                  "poids_exam":0.6,
                  "moy":0
               },
               {
                  "name":"Algèbre2",
                  "title":"Algèbre 2",
                  "coef":2,
                  "credit":4,
                  "poids":[
                     60,
                     40,
                     0
                  ],
                  "poids_tp":0,
                  "poids_td":0.4,
                  "poids_exam":0.6,
                  "moy":0
               }
            ],
            "coef":5,
            "credit":0,
            "credits_origine":10,
            "moy":0
         },
         {
            "name":"U2_S2",
            "title":"Fondamentale",
            "modules":[
               {
                  "name":"EM",
                  "title":"Electricité et magnétisme",
                  "coef":3,
                  "credit":6,
                  "poids":[
                     60,
                     40,
                     0
                  ],
                  "poids_tp":0,
                  "poids_td":0.4,
                  "poids_exam":0.6,
                  "moy":0
               },
               {
                  "name":"therm",
                  "title":"Thermodynamique",
                  "coef":3,
                  "credit":6,
                  "poids":[
                     60,
                     40,
                     0
                  ],
                  "poids_tp":0,
                  "poids_td":0.4,
                  "poids_exam":0.6,
                  "moy":0
               }
            ],
            "coef":6,
            "credit":0,
            "credits_origine":12,
            "moy":0
         },
         {
            "name":"U3_S2",
            "title":"Méthodologique",
            "modules":[
               {
                  "name":"TPEM",
                  "title":"TP Electricité et magnétisme",
                  "coef":1,
                  "credit":2,
                  "poids":[
                     0,
                     0,
                     100
                  ],
                  "poids_tp":1,
                  "poids_td":0,
                  "poids_exam":0,
                  "moy":0
               },
               {
                  "name":"TPTherm",
                  "title":"TP Thermodynamique",
                  "coef":1,
                  "credit":2,
                  "poids":[
                     0,
                     0,
                     100
                  ],
                  "poids_tp":1,
                  "poids_td":0,
                  "poids_exam":0,
                  "moy":0
               },
               {
                  "name":"info2",
                  "title":"Initiation à la programmation",
                  "coef":2,
                  "credit":2,
                  "poids":[
                     60,
                     0,
                     40
                  ],
                  "poids_tp":0.4,
                  "poids_td":0,
                  "poids_exam":0.6,
                  "moy":0
               }
            ],
            "coef":4,
            "credit":0,
            "credits_origine":6,
            "moy":0
         },
         {
            "name":"U4_S2",
            "title":"Transversale",
            "modules":[
               {
                  "name":"LLOS",
                  "title":"Logiciels libres -open sources",
                  "coef":2,
                  "credit":2,
                  "poids":[
                     100,
                     0,
                     0
                  ],
                  "poids_tp":0,
                  "poids_td":0,
                  "poids_exam":1,
                  "moy":0
               }
            ],
            "coef":2,
            "credit":0,
            "credits_origine":2,
            "moy":0
         }
      ],
      "moy":0,
      "coef":17,
      "credits_origine":30
   },
   "moy":0
}
