{
   "name":"L3SI",
    "fullname": "Systèmes Informatiques",
"domain":"Mathematiques et Informatique",
"startdate":"2018",
"expired":"",
"cycle":"licence",
"level":"3",
"branch":"Informatique",
"universities": [],
   "semestre1":{
      "name":"S5",
      "unites":[
         {
            "name":"U1_S1",
            "title":"Fondamentale1",
            "modules":[
               {
                  "name":"SE",
                  "title":"Systèmes d'exploitation",
                  "coef":3,
                  "credit":5,
                  "poids":[
                     60,
                     20,
                     20
                  ],
                  "poids_tp":0.2,
                  "poids_td":0.2,
                  "poids_exam":0.6,
                  "moy":0
               },
               {
                  "name":"Comp",
                  "title":"Compilation",
                  "coef":3,
                  "credit":5,
                  "poids":[
                     60,
                     20,
                     20
                  ],
                  "poids_tp":0.2,
                  "poids_td":0.2,
                  "poids_exam":0.6,
                  "moy":0
               }
            ],
            "coef":6,
            "credit":0,
            "credits_origine":10,
            "moy":0
         },
         {
            "name":"U2_S1",
            "title":"Fondamentale2",
            "modules":[
               {
                  "name":"GL2",
                  "title":"Génie Logiciel",
                  "coef":3,
                  "credit":5,
                  "poids":[
                     60,
                     20,
                     20
                  ],
                  "poids_tp":0.2,
                  "poids_td":0.2,
                  "poids_exam":0.6,
                  "moy":0
               },
               {
                  "name":"IHM",
                  "title":"IHM",
                  "coef":3,
                  "credit":5,
                  "poids":[
                     60,
                     20,
                     20
                  ],
                  "poids_tp":0.2,
                  "poids_td":0.2,
                  "poids_exam":0.6,
                  "moy":0
               }
            ],
            "coef":6,
            "credit":0,
            "credits_origine":10,
            "moy":0
         },
         {
            "name":"U3_S1",
            "title":"Méthodologique",
            "modules":[
               {
                  "name":"PL",
                  "title":"Programmation linéaire",
                  "coef":2,
                  "credit":4,
                  "poids":[
                     60,
                     40,
                     0
                  ],
                  "poids_tp":0,
                  "poids_td":0.4,
                  "poids_exam":0.6,
                  "moy":0
               },
               {
                  "name":"Proba",
                  "title":"Probabilités",
                  "coef":2,
                  "credit":4,
                  "poids":[
                     60,
                     40,
                     0
                  ],
                  "poids_tp":0,
                  "poids_td":0.4,
                  "poids_exam":0.6,
                  "moy":0
               }
            ],
            "coef":4,
            "credit":0,
            "credits_origine":8,
            "moy":0
         },
         {
            "name":"U4_S1",
            "title":"Transversale",
            "modules":[
               {
                  "name":"Econum",
                  "title":"Economie numérique et veille stratégique",
                  "coef":1,
                  "credit":2,
                  "poids":[
                     0,
                     100,
                     0
                  ],
                  "poids_tp":0,
                  "poids_td":1,
                  "poids_exam":0,
                  "moy":0
               }
            ],
            "coef":1,
            "credit":0,
            "credits_origine":2,
            "moy":0
         }
      ],
      "moy":0,
      "coef":17,
      "credits_origine":30
   },
   "semestre2":{
      "name":"S6",
      "unites":[
         {
            "name":"U1_S2",
            "title":"Fondamental1",
            "modules":[
               {
                  "name":"mobile",
                  "title":"Applications Mobile",
                  "coef":3,
                  "credit":5,
                  "poids":[
                     60,
                     0,
                     40
                  ],
                  "poids_tp":0.4,
                  "poids_td":0,
                  "poids_exam":0.6,
                  "moy":0
               },
               {
                  "name":"secu",
                  "title":"Sécurité Informatique",
                  "coef":3,
                  "credit":5,
                  "poids":[
                     60,
                     40,
                     0
                  ],
                  "poids_tp":0,
                  "poids_td":0.4,
                  "poids_exam":0.6,
                  "moy":0
               }
            ],
            "coef":6,
            "credit":0,
            "credits_origine":10,
            "moy":0
         },
         {
            "name":"U2_S2",
            "title":"Fondamentale2",
            "modules":[
               {
                  "name":"IA",
                  "title":"Intelligenece Artificielle",
                  "coef":3,
                  "credit":5,
                  "poids":[
                     60,
                     0,
                     40
                  ],
                  "poids_tp":0.4,
                  "poids_td":0,
                  "poids_exam":0.6,
                  "moy":0
               },
               {
                  "name":"DSS",
                  "title":"Données semi structurées",
                  "coef":3,
                  "credit":5,
                  "poids":[
                     60,
                     0,
                     40
                  ],
                  "poids_tp":0.4,
                  "poids_td":0,
                  "poids_exam":0.6,
                  "moy":0
               }
            ],
            "coef":6,
            "credit":0,
            "credits_origine":10,
            "moy":0
         },
         {
            "name":"U3_S2",
            "title":"Méthodologique",
            "modules":[
               {
                  "name":"projet",
                  "title":"Projet",
                  "coef":3,
                  "credit":6,
                  "poids":[
                     100,
                     0,
                     0
                  ],
                  "poids_tp":0,
                  "poids_td":0,
                  "poids_exam":1,
                  "moy":0
               },
               {
                  "name":"redaction",
                  "title":"Rédaction Scientifique",
                  "coef":1,
                  "credit":2,
                  "poids":[
                     0,
                     100,
                     0
                  ],
                  "poids_tp":0,
                  "poids_td":1,
                  "poids_exam":0,
                  "moy":0
               }
            ],
            "coef":4,
            "credit":0,
            "credits_origine":8,
            "moy":0
         },
         {
            "name":"U4_S2",
            "title":"Transversale",
            "modules":[
               {
                  "name":"startup",
                  "title":" Créer une startup",
                  "coef":1,
                  "credit":2,
                  "poids":[
                     100,
                     0,
                     0
                  ],
                  "poids_tp":0,
                  "poids_td":0,
                  "poids_exam":1,
                  "moy":0
               }
            ],
            "coef":1,
            "credit":0,
            "credits_origine":2,
            "moy":0
         }
      ],
      "moy":0,
      "coef":17,
      "credits_origine":30
   },
   "moy":0
}
